ethosu/mlw_codec.cpython-39-i386-linux-gnu.so
ethosu/regor.cpython-39-i386-linux-gnu.so
ethosu/config_files/Arm/vela.ini
ethosu/vela/__init__.py
ethosu/vela/__main__.py
ethosu/vela/_version.py
ethosu/vela/api.py
ethosu/vela/architecture_allocator.py
ethosu/vela/architecture_features.py
ethosu/vela/cascade_builder.py
ethosu/vela/compiler_driver.py
ethosu/vela/data_type.py
ethosu/vela/debug_database.py
ethosu/vela/driver_actions.py
ethosu/vela/errors.py
ethosu/vela/extract_npu_subgraphs.py
ethosu/vela/fp_math.py
ethosu/vela/graph_optimiser.py
ethosu/vela/graph_optimiser_util.py
ethosu/vela/greedy_allocation.py
ethosu/vela/high_level_command_stream.py
ethosu/vela/high_level_command_stream_generator.py
ethosu/vela/high_level_command_to_npu_op.py
ethosu/vela/hillclimb_allocation.py
ethosu/vela/live_range.py
ethosu/vela/lstm.py
ethosu/vela/lut.py
ethosu/vela/mark_tensors.py
ethosu/vela/model_reader.py
ethosu/vela/nn_graph.py
ethosu/vela/npu_performance.py
ethosu/vela/npu_serialisation.py
ethosu/vela/numeric_util.py
ethosu/vela/operation.py
ethosu/vela/operation_util.py
ethosu/vela/pass_packing.py
ethosu/vela/range_set.py
ethosu/vela/rawdata_writer.py
ethosu/vela/reader_util.py
ethosu/vela/register_command_stream_generator.py
ethosu/vela/register_command_stream_util.py
ethosu/vela/rewrite_graph.py
ethosu/vela/scaling.py
ethosu/vela/scheduler.py
ethosu/vela/shape4d.py
ethosu/vela/softmax.py
ethosu/vela/stats_writer.py
ethosu/vela/supported_operators_util.py
ethosu/vela/tensor.py
ethosu/vela/tensor_allocation.py
ethosu/vela/tflite_graph_optimiser.py
ethosu/vela/tflite_mapping.py
ethosu/vela/tflite_model_semantic.py
ethosu/vela/tflite_reader.py
ethosu/vela/tflite_supported_operators.py
ethosu/vela/tflite_writer.py
ethosu/vela/tosa_graph_optimiser.py
ethosu/vela/tosa_mapping.py
ethosu/vela/tosa_model_semantic.py
ethosu/vela/tosa_reader.py
ethosu/vela/tosa_supported_operators.py
ethosu/vela/utils.py
ethos_u_vela-4.4.1.dist-info/METADATA
ethos_u_vela-4.4.1.dist-info/WHEEL
ethos_u_vela-4.4.1.dist-info/entry_points.txt
ethos_u_vela-4.4.1.dist-info/top_level.txt
ethos_u_vela-4.4.1.dist-info/RECORD
ethos_u_vela-4.4.1.dist-info/licenses/LICENSE.txt
