Metadata-Version: 2.4
Name: ethos-u-vela
Version: 4.4.1
Summary: Neural network model compiler for Arm Ethos-U NPUs
Author-email: Arm Ltd <mlg-vela@arm.com>
License-Expression: Apache-2.0
Project-URL: Homepage, https://gitlab.arm.com/artificial-intelligence/ethos-u/ethos-u-vela
Keywords: ethos-u,vela,tosa,tflite,npu,compiler
Classifier: Development Status :: 5 - Production/Stable
Classifier: Intended Audience :: Developers
Classifier: Operating System :: MacOS
Classifier: Operating System :: Microsoft :: Windows
Classifier: Operating System :: POSIX :: Linux
Classifier: Programming Language :: C
Classifier: Programming Language :: C++
Classifier: Programming Language :: Python :: 3
Classifier: Topic :: Scientific/Engineering :: Artificial Intelligence
Classifier: Topic :: Software Development :: Compilers
Requires-Python: ~=3.9
License-File: LICENSE.txt
Requires-Dist: flatbuffers==24.3.25
Requires-Dist: numpy>=1.23.0
Requires-Dist: lxml<6.0.1,>=4.7.1
Requires-Dist: lxml<5.3.2,>=4.7.1; sys_platform == "win32"
Provides-Extra: dev
Requires-Dist: pytest; extra == "dev"
Requires-Dist: pytest-cov; extra == "dev"
Requires-Dist: pre-commit; extra == "dev"
Requires-Dist: build; extra == "dev"
Requires-Dist: setuptools_scm[toml]~=7.1.0; extra == "dev"
Dynamic: description
Dynamic: description-content-type
Dynamic: license-file
